phiton/__init__.py
phiton/__main__.py
phiton/__version__.py
phiton/cli.py
phiton/config.py
phiton/constants.py
phiton/dephitonize.py
phiton/phitonize.py
phiton/utils.py
phiton-2.7.5.dist-info/METADATA
phiton-2.7.5.dist-info/WHEEL
phiton-2.7.5.dist-info/entry_points.txt
phiton-2.7.5.dist-info/licenses/LICENSE
phiton-2.7.5.dist-info/RECORD
