Metadata-Version: 2.4
Name: phiton
Version: 2.7.5
Project-URL: Documentation, https://github.com/twardoch/phiton#readme
Project-URL: Issues, https://github.com/twardoch/phiton/issues
Project-URL: Source, https://github.com/twardoch/phiton
Author-email: Adam Twardoch <adam+github@twardoch.com>
License-Expression: MIT
License-File: LICENSE
Classifier: Development Status :: 4 - Beta
Classifier: Programming Language :: Python
Classifier: Programming Language :: Python :: 3.10
Classifier: Programming Language :: Python :: 3.11
Classifier: Programming Language :: Python :: 3.12
Classifier: Programming Language :: Python :: Implementation :: CPython
Classifier: Programming Language :: Python :: Implementation :: PyPy
Requires-Python: >=3.10
Requires-Dist: fire>=0.7.0
Requires-Dist: loguru>=0.7.3
Requires-Dist: rich>=13.9.4
Provides-Extra: all
Requires-Dist: black>=25.1.0; extra == 'all'
Requires-Dist: fire>=0.7.0; extra == 'all'
Requires-Dist: hatch>=1.14.0; extra == 'all'
Requires-Dist: isort>=6.0.1; extra == 'all'
Requires-Dist: loguru>=0.7.3; extra == 'all'
Requires-Dist: matplotlib>=3.10.1; extra == 'all'
Requires-Dist: mypy>=1.15.0; extra == 'all'
Requires-Dist: numpy>=2.2.3; extra == 'all'
Requires-Dist: pandas>=2.2.3; extra == 'all'
Requires-Dist: pre-commit>=4.1.0; extra == 'all'
Requires-Dist: pytest-benchmark>=5.1.0; extra == 'all'
Requires-Dist: pytest-cov>=6.0.0; extra == 'all'
Requires-Dist: pytest-xdist>=3.6.1; extra == 'all'
Requires-Dist: pytest>=8.3.4; extra == 'all'
Requires-Dist: pyupgrade>=3.19.1; extra == 'all'
Requires-Dist: rich>=13.9.4; extra == 'all'
Requires-Dist: ruff>=0.9.9; extra == 'all'
Requires-Dist: uv>=0.6.3; extra == 'all'
Provides-Extra: dev
Requires-Dist: black>=25.1.0; extra == 'dev'
Requires-Dist: hatch>=1.14.0; extra == 'dev'
Requires-Dist: isort>=6.0.1; extra == 'dev'
Requires-Dist: mypy>=1.15.0; extra == 'dev'
Requires-Dist: pre-commit>=4.1.0; extra == 'dev'
Requires-Dist: pyupgrade>=3.19.1; extra == 'dev'
Requires-Dist: ruff>=0.9.9; extra == 'dev'
Requires-Dist: uv>=0.6.3; extra == 'dev'
Provides-Extra: test
Requires-Dist: matplotlib>=3.10.1; extra == 'test'
Requires-Dist: numpy>=2.2.3; extra == 'test'
Requires-Dist: pandas>=2.2.3; extra == 'test'
Requires-Dist: pytest-benchmark>=5.1.0; extra == 'test'
Requires-Dist: pytest-cov>=6.0.0; extra == 'test'
Requires-Dist: pytest-xdist>=3.6.1; extra == 'test'
Requires-Dist: pytest>=8.3.4; extra == 'test'
